raccoonai/__init__.py
raccoonai/_base_client.py
raccoonai/_client.py
raccoonai/_compat.py
raccoonai/_constants.py
raccoonai/_exceptions.py
raccoonai/_files.py
raccoonai/_models.py
raccoonai/_qs.py
raccoonai/_resource.py
raccoonai/_response.py
raccoonai/_streaming.py
raccoonai/_types.py
raccoonai/_version.py
raccoonai/py.typed
raccoonai/_utils/__init__.py
raccoonai/_utils/_compat.py
raccoonai/_utils/_datetime_parse.py
raccoonai/_utils/_logs.py
raccoonai/_utils/_proxy.py
raccoonai/_utils/_reflection.py
raccoonai/_utils/_resources_proxy.py
raccoonai/_utils/_streams.py
raccoonai/_utils/_sync.py
raccoonai/_utils/_transform.py
raccoonai/_utils/_typing.py
raccoonai/_utils/_utils.py
raccoonai/lib/.keep
raccoonai/resources/__init__.py
raccoonai/resources/fleet/__init__.py
raccoonai/resources/fleet/extensions.py
raccoonai/resources/fleet/fleet.py
raccoonai/resources/fleet/sessions.py
raccoonai/resources/lam/__init__.py
raccoonai/resources/lam/lam.py
raccoonai/resources/lam/tasks.py
raccoonai/resources/tail/__init__.py
raccoonai/resources/tail/apps.py
raccoonai/resources/tail/tail.py
raccoonai/resources/tail/users.py
raccoonai/types/__init__.py
raccoonai/types/lam_run_params.py
raccoonai/types/lam_run_response.py
raccoonai/types/fleet/__init__.py
raccoonai/types/fleet/extension_all_response.py
raccoonai/types/fleet/extension_get_response.py
raccoonai/types/fleet/extension_upload_params.py
raccoonai/types/fleet/extension_upload_response.py
raccoonai/types/fleet/session_all_params.py
raccoonai/types/fleet/session_all_response.py
raccoonai/types/fleet/session_create_params.py
raccoonai/types/fleet/session_create_response.py
raccoonai/types/fleet/session_logs_response.py
raccoonai/types/fleet/session_media_response.py
raccoonai/types/fleet/session_status_response.py
raccoonai/types/fleet/session_terminate_response.py
raccoonai/types/lam/__init__.py
raccoonai/types/lam/task_all_params.py
raccoonai/types/lam/task_all_response.py
raccoonai/types/lam/task_media_response.py
raccoonai-0.1.0a19.dist-info/METADATA
raccoonai-0.1.0a19.dist-info/WHEEL
raccoonai-0.1.0a19.dist-info/licenses/LICENSE
raccoonai-0.1.0a19.dist-info/RECORD
